{
  "devices": [
    {
      "classes": [
        {
          "capability_names": [
            "runtime-supported"
          ],
          "class_capability_count": 1,
          "dma_signals": [],
          "instance_capability_count": 0,
          "peripheral_class": "adc",
          "peripheral_count": 2,
          "peripherals": [
            "ADC1",
            "ADC2"
          ],
          "present": true
        },
        {
          "capability_names": [
            "runtime-supported"
          ],
          "class_capability_count": 1,
          "dma_signals": [],
          "instance_capability_count": 0,
          "peripheral_class": "can",
          "peripheral_count": 3,
          "peripherals": [
            "CAN1",
            "CAN2",
            "CAN3"
          ],
          "present": true
        },
        {
          "capability_names": [
            "runtime-supported"
          ],
          "class_capability_count": 1,
          "dma_signals": [],
          "instance_capability_count": 0,
          "peripheral_class": "dma",
          "peripheral_count": 1,
          "peripherals": [
            "DMA0"
          ],
          "present": true
        },
        {
          "capability_names": [
            "runtime-supported"
          ],
          "class_capability_count": 1,
          "dma_signals": [],
          "instance_capability_count": 0,
          "peripheral_class": "dma-router",
          "peripheral_count": 1,
          "peripherals": [
            "DMAMUX1"
          ],
          "present": true
        },
        {
          "capability_names": [
            "runtime-supported"
          ],
          "class_capability_count": 1,
          "dma_signals": [],
          "instance_capability_count": 0,
          "peripheral_class": "eth",
          "peripheral_count": 2,
          "peripherals": [
            "ENET",
            "ENET2"
          ],
          "present": true
        },
        {
          "capability_names": [
            "available-signal",
            "runtime-supported",
            "signal-role"
          ],
          "class_capability_count": 33,
          "dma_signals": [],
          "instance_capability_count": 124,
          "peripheral_class": "gpio",
          "peripheral_count": 10,
          "peripherals": [
            "GPIO1",
            "GPIO10",
            "GPIO2",
            "GPIO3",
            "GPIO4",
            "GPIO5",
            "GPIO6",
            "GPIO7",
            "GPIO8",
            "GPIO9"
          ],
          "present": true
        },
        {
          "capability_names": [
            "runtime-supported"
          ],
          "class_capability_count": 1,
          "dma_signals": [],
          "instance_capability_count": 0,
          "peripheral_class": "pwm",
          "peripheral_count": 4,
          "peripherals": [
            "PWM1",
            "PWM2",
            "PWM3",
            "PWM4"
          ],
          "present": true
        },
        {
          "capability_names": [
            "available-signal",
            "runtime-supported",
            "signal-role"
          ],
          "class_capability_count": 6,
          "dma_signals": [],
          "instance_capability_count": 17,
          "peripheral_class": "spi",
          "peripheral_count": 4,
          "peripherals": [
            "LPSPI1",
            "LPSPI2",
            "LPSPI3",
            "LPSPI4"
          ],
          "present": true
        },
        {
          "capability_names": [
            "runtime-supported"
          ],
          "class_capability_count": 1,
          "dma_signals": [],
          "instance_capability_count": 0,
          "peripheral_class": "timer",
          "peripheral_count": 3,
          "peripherals": [
            "GPT1",
            "GPT2",
            "PIT"
          ],
          "present": true
        },
        {
          "capability_names": [
            "available-signal",
            "runtime-supported",
            "signal-role"
          ],
          "class_capability_count": 5,
          "dma_signals": [],
          "instance_capability_count": 32,
          "peripheral_class": "uart",
          "peripheral_count": 8,
          "peripherals": [
            "LPUART1",
            "LPUART2",
            "LPUART3",
            "LPUART4",
            "LPUART5",
            "LPUART6",
            "LPUART7",
            "LPUART8"
          ],
          "present": true
        },
        {
          "capability_names": [
            "runtime-supported"
          ],
          "class_capability_count": 1,
          "dma_signals": [],
          "instance_capability_count": 0,
          "peripheral_class": "usb",
          "peripheral_count": 2,
          "peripherals": [
            "USB1",
            "USB2"
          ],
          "present": true
        },
        {
          "capability_names": [
            "runtime-supported"
          ],
          "class_capability_count": 1,
          "dma_signals": [],
          "instance_capability_count": 0,
          "peripheral_class": "watchdog",
          "peripheral_count": 3,
          "peripherals": [
            "RTWDOG",
            "WDOG1",
            "WDOG2"
          ],
          "present": true
        }
      ],
      "device": "mimxrt1062",
      "package": "bga196"
    },
    {
      "classes": [
        {
          "capability_names": [
            "runtime-supported"
          ],
          "class_capability_count": 1,
          "dma_signals": [],
          "instance_capability_count": 0,
          "peripheral_class": "adc",
          "peripheral_count": 2,
          "peripherals": [
            "ADC1",
            "ADC2"
          ],
          "present": true
        },
        {
          "capability_names": [
            "runtime-supported"
          ],
          "class_capability_count": 1,
          "dma_signals": [],
          "instance_capability_count": 0,
          "peripheral_class": "can",
          "peripheral_count": 3,
          "peripherals": [
            "CAN1",
            "CAN2",
            "CAN3"
          ],
          "present": true
        },
        {
          "capability_names": [
            "runtime-supported"
          ],
          "class_capability_count": 1,
          "dma_signals": [],
          "instance_capability_count": 0,
          "peripheral_class": "dma",
          "peripheral_count": 1,
          "peripherals": [
            "DMA0"
          ],
          "present": true
        },
        {
          "capability_names": [
            "runtime-supported"
          ],
          "class_capability_count": 1,
          "dma_signals": [],
          "instance_capability_count": 0,
          "peripheral_class": "dma-router",
          "peripheral_count": 1,
          "peripherals": [
            "DMAMUX1"
          ],
          "present": true
        },
        {
          "capability_names": [
            "runtime-supported"
          ],
          "class_capability_count": 1,
          "dma_signals": [],
          "instance_capability_count": 0,
          "peripheral_class": "eth",
          "peripheral_count": 2,
          "peripherals": [
            "ENET",
            "ENET2"
          ],
          "present": true
        },
        {
          "capability_names": [
            "available-signal",
            "runtime-supported",
            "signal-role"
          ],
          "class_capability_count": 33,
          "dma_signals": [],
          "instance_capability_count": 124,
          "peripheral_class": "gpio",
          "peripheral_count": 10,
          "peripherals": [
            "GPIO1",
            "GPIO10",
            "GPIO2",
            "GPIO3",
            "GPIO4",
            "GPIO5",
            "GPIO6",
            "GPIO7",
            "GPIO8",
            "GPIO9"
          ],
          "present": true
        },
        {
          "capability_names": [
            "runtime-supported"
          ],
          "class_capability_count": 1,
          "dma_signals": [],
          "instance_capability_count": 0,
          "peripheral_class": "pwm",
          "peripheral_count": 4,
          "peripherals": [
            "PWM1",
            "PWM2",
            "PWM3",
            "PWM4"
          ],
          "present": true
        },
        {
          "capability_names": [
            "available-signal",
            "runtime-supported",
            "signal-role"
          ],
          "class_capability_count": 6,
          "dma_signals": [],
          "instance_capability_count": 17,
          "peripheral_class": "spi",
          "peripheral_count": 4,
          "peripherals": [
            "LPSPI1",
            "LPSPI2",
            "LPSPI3",
            "LPSPI4"
          ],
          "present": true
        },
        {
          "capability_names": [
            "runtime-supported"
          ],
          "class_capability_count": 1,
          "dma_signals": [],
          "instance_capability_count": 0,
          "peripheral_class": "timer",
          "peripheral_count": 3,
          "peripherals": [
            "GPT1",
            "GPT2",
            "PIT"
          ],
          "present": true
        },
        {
          "capability_names": [
            "available-signal",
            "runtime-supported",
            "signal-role"
          ],
          "class_capability_count": 5,
          "dma_signals": [],
          "instance_capability_count": 32,
          "peripheral_class": "uart",
          "peripheral_count": 8,
          "peripherals": [
            "LPUART1",
            "LPUART2",
            "LPUART3",
            "LPUART4",
            "LPUART5",
            "LPUART6",
            "LPUART7",
            "LPUART8"
          ],
          "present": true
        },
        {
          "capability_names": [
            "runtime-supported"
          ],
          "class_capability_count": 1,
          "dma_signals": [],
          "instance_capability_count": 0,
          "peripheral_class": "usb",
          "peripheral_count": 2,
          "peripherals": [
            "USB1",
            "USB2"
          ],
          "present": true
        },
        {
          "capability_names": [
            "runtime-supported"
          ],
          "class_capability_count": 1,
          "dma_signals": [],
          "instance_capability_count": 0,
          "peripheral_class": "watchdog",
          "peripheral_count": 3,
          "peripherals": [
            "RTWDOG",
            "WDOG1",
            "WDOG2"
          ],
          "present": true
        }
      ],
      "device": "mimxrt1064",
      "package": "bga196"
    }
  ],
  "driver_classes": [
    "adc",
    "can",
    "dma",
    "dma-router",
    "eth",
    "gpio",
    "pwm",
    "spi",
    "timer",
    "uart",
    "usb",
    "watchdog"
  ],
  "family": "imxrt1060",
  "family_dir": "nxp/imxrt1060",
  "report_id": "runtime-compatibility-matrix-v1",
  "vendor": "nxp"
}
